wolfsoftware/shamir_secret_sharing/__init__.py
wolfsoftware/shamir_secret_sharing/cli.py
wolfsoftware/shamir_secret_sharing/config.py
wolfsoftware/shamir_secret_sharing/constants.py
wolfsoftware/shamir_secret_sharing/create.py
wolfsoftware/shamir_secret_sharing/exceptions.py
wolfsoftware/shamir_secret_sharing/globals.py
wolfsoftware/shamir_secret_sharing/main.py
wolfsoftware/shamir_secret_sharing/maths.py
wolfsoftware/shamir_secret_sharing/reconstruct.py
wolfsoftware/shamir_secret_sharing/utils.py
wolfsoftware.shamir_secret_sharing-0.1.3.dist-info/LICENSE.md
wolfsoftware.shamir_secret_sharing-0.1.3.dist-info/METADATA
wolfsoftware.shamir_secret_sharing-0.1.3.dist-info/WHEEL
wolfsoftware.shamir_secret_sharing-0.1.3.dist-info/entry_points.txt
wolfsoftware.shamir_secret_sharing-0.1.3.dist-info/top_level.txt
wolfsoftware.shamir_secret_sharing-0.1.3.dist-info/RECORD
