Metadata-Version: 2.1
Name: wolfsoftware.shamir-secret-sharing
Version: 0.1.3
Summary: A CLI implementation of Shamir's secret sharing.
Home-page: https://github.com/GreyTeamToolbox/shamir-secret-sharing-package
Author: Wolf Software
Author-email: pypi@wolfsoftware.com
Project-URL: Source, https://github.com/GreyTeamToolbox/shamir-secret-sharing-package
Project-URL: Tracker, https://github.com/GreyTeamToolbox/shamir-secret-sharing-package/issues/
Project-URL: Documentation, https://github.com/GreyTeamToolbox/shamir-secret-sharing-package
Project-URL: Sponsor, https://github.com/sponsors/WolfSoftware
Classifier: Environment :: Console
Classifier: Intended Audience :: Developers
Classifier: Intended Audience :: Education
Classifier: Intended Audience :: Information Technology
Classifier: Intended Audience :: Science/Research
Classifier: Intended Audience :: System Administrators
Classifier: Programming Language :: Python :: 3
Classifier: License :: OSI Approved :: MIT License
Classifier: Operating System :: OS Independent
Classifier: Topic :: Software Development
Requires-Python: >=3.9
License-File: LICENSE.md
Requires-Dist: colorama ==0.4.6
Requires-Dist: wolfsoftware.notify ==0.1.2
